pydepict/__init__.py
pydepict/__main__.py
pydepict/consts.py
pydepict/depicter.py
pydepict/errors.py
pydepict/models.py
pydepict/parser.py
pydepict/renderer.py
pydepict/utils.py
pydepict-0.1.1.post2.dist-info/LICENSE
pydepict-0.1.1.post2.dist-info/LICENSE.networkx
pydepict-0.1.1.post2.dist-info/LICENSE.pygame
pydepict-0.1.1.post2.dist-info/METADATA
pydepict-0.1.1.post2.dist-info/WHEEL
pydepict-0.1.1.post2.dist-info/entry_points.txt
pydepict-0.1.1.post2.dist-info/top_level.txt
pydepict-0.1.1.post2.dist-info/RECORD
