Metadata-Version: 2.1
Name: pydepict
Version: 0.1.1.post2
Summary: Library for SMILES parsing and molecular graph depiction.
Home-page: https://github.com/WilliamWFLee/pydepict
Author: William Lee
Author-email: wwflee1@sheffield.ac.uk
License: MIT
Classifier: Development Status :: 3 - Alpha
Classifier: Intended Audience :: Science/Research
Classifier: License :: OSI Approved :: MIT License
Classifier: Operating System :: MacOS
Classifier: Operating System :: Microsoft :: Windows
Classifier: Operating System :: POSIX
Classifier: Operating System :: Unix
Classifier: Programming Language :: Python
Classifier: Programming Language :: Python :: 3 :: Only
Classifier: Programming Language :: Python :: 3.7
Classifier: Programming Language :: Python :: 3.8
Classifier: Programming Language :: Python :: 3.9
Classifier: Programming Language :: Python :: 3.10
Classifier: Programming Language :: Python :: Implementation :: CPython
Classifier: Topic :: Scientific/Engineering :: Chemistry
Classifier: Typing :: Typed
Requires-Python: >=3.7
License-File: LICENSE
License-File: LICENSE.networkx
License-File: LICENSE.pygame
Requires-Dist: networkx (==2.6.3)
Requires-Dist: pygame (==2.1.2)
Provides-Extra: dev
Requires-Dist: flake8 (==4.0.1) ; extra == 'dev'
Requires-Dist: black (==22.3.0) ; extra == 'dev'
Provides-Extra: dist
Requires-Dist: build (==0.7.0) ; extra == 'dist'
Requires-Dist: twine (==4.0.0) ; extra == 'dist'
Requires-Dist: setuptools (>=42) ; extra == 'dist'
Provides-Extra: test
Requires-Dist: pytest (==7.0.1) ; extra == 'test'
Requires-Dist: pytest-order (==1.0.1) ; extra == 'test'
Requires-Dist: pytest-mock (==3.7.0) ; extra == 'test'
Requires-Dist: pytest-cov (==3.0.0) ; extra == 'test'
